pyHM/__init__.py
pyHM/mouse.py
pyHM-0.0.7.dist-info/LICENCE
pyHM-0.0.7.dist-info/METADATA
pyHM-0.0.7.dist-info/WHEEL
pyHM-0.0.7.dist-info/top_level.txt
pyHM-0.0.7.dist-info/RECORD
