Metadata-Version: 2.1
Name: pyHM
Version: 0.0.7
Summary: Python Human Movement is a python package which imitates human movements
Home-page: https://bitbucket.org/joetilsed/pyHM/
Author: Joe Tilsed
Author-email: Joe@Tilsed.com
Keywords: pyHM python human movements
Classifier: Programming Language :: Python :: 3.8
Classifier: Natural Language :: English
Classifier: Intended Audience :: Developers
Classifier: License :: OSI Approved :: MIT License
Classifier: Operating System :: OS Independent
License-File: LICENCE
Requires-Dist: numpy (>=1.20.1)
Requires-Dist: scipy (>=1.6.1)
Requires-Dist: PyAutoGUI (>=0.9.52)
